odoo9_addon_stock_reserve-9.0.1.0.0-py2.7-nspkg.pth
odoo_addons/stock_reserve/__openerp__.py
odoo_addons/stock_reserve/__init__.py
odoo_addons/stock_reserve/README.rst
odoo_addons/stock_reserve/security/ir.model.access.csv
odoo_addons/stock_reserve/migrations/0.2/post-migration.py
odoo_addons/stock_reserve/view/product.xml
odoo_addons/stock_reserve/view/stock_reserve.xml
odoo_addons/stock_reserve/i18n/es.po
odoo_addons/stock_reserve/i18n/fr.po
odoo_addons/stock_reserve/i18n/stock_reserve.pot
odoo_addons/stock_reserve/i18n/fi.po
odoo_addons/stock_reserve/model/product.py
odoo_addons/stock_reserve/model/__init__.py
odoo_addons/stock_reserve/model/stock_reserve.py
odoo_addons/stock_reserve/test/stock_reserve.yml
odoo_addons/stock_reserve/data/stock_data.xml
odoo9_addon_stock_reserve-9.0.1.0.0.dist-info/top_level.txt
odoo9_addon_stock_reserve-9.0.1.0.0.dist-info/WHEEL
odoo9_addon_stock_reserve-9.0.1.0.0.dist-info/RECORD
odoo9_addon_stock_reserve-9.0.1.0.0.dist-info/metadata.json
odoo9_addon_stock_reserve-9.0.1.0.0.dist-info/DESCRIPTION.rst
odoo9_addon_stock_reserve-9.0.1.0.0.dist-info/METADATA
odoo9_addon_stock_reserve-9.0.1.0.0.dist-info/namespace_packages.txt
